adder.v
// Adder circuit
`define AND and #50
`define OR or #50
`define XOR xor #50
`define NOT not #50

module structuralFullAdder
(
    output sum,
    output carryout,
    input a,
    input b,
    input carryin

);
    wire xor0, and0, and1;
    // Single bit adder with carryin / carryout
    `XOR xorgate(xor0,a,b);
    `AND andgate(and0,a,b);
    `XOR xorgate(sum,xor0,carryin);
    `AND andgate(and1,xor0,carryin);
    `OR orgate(carryout,and0,and1);
endmodule

module FullAdder4bit
(
  output[3:0] sum,  // 2's complement sum of a and b
  output carryout,  // Carry out of the summation of a and b
  output overflow,  // True if the calculation resulted in an overflow
  input[3:0] a,     // First operand in 2's complement format
  input[3:0] b      // Second operand in 2's complement format
);
    // Your Code Here
    wire carryout0, carryout1, carryout2;
    structuralFullAdder adder0 (sum[0], carryout0, a[0], b[0], 0);
    structuralFullAdder adder1 (sum[1], carryout1, a[1], b[1], carryout0);
    structuralFullAdder adder2 (sum[2], carryout2, a[2], b[2], carryout1);
    structuralFullAdder adder3 (sum[3], carryout,  a[3], b[3], carryout2);
    
    wire negand, posand, a3inv, b3inv, s3inv;
    `NOT a3inv(a3inv, a[3]);
    `NOT b3inv(b3inv, b[3]);
    `NOT s3inv(s3inv, sum[3]);
    `AND posand(posand, a3inv, b3inv, carryout2);
    `AND negand(negand, a[3], b[3], s3inv);
    `OR overflowgate(overflow, posand, negand);

endmodule

adder.t.v
// Adder testbench
`timescale 1 ns / 1 ps
`include "adder.v"

module testFullAdder();
    reg [3:0] a, b;
    wire [3:0] sum;
    wire carryout, overflow;

    FullAdder4bit fulladder (sum, carryout, overflow, a, b);

    initial begin
    $dumpfile("adder.vcd");
    $dumpvars;

    $display("a    | b    | sum   cout ovfl | Esum Ecout Eovfl");
    /*
    Negatives

    -2 + -3 = -5 => yes carryout, no overflow
    -1 + -4 = -5 =>

    */
    a = 4'b1110; b = 4'b1101; #1000 // -2 + -3 = -5
    $display("%b | %b | %b  %b    %b    | 1011 1     0", a, b, sum, carryout, overflow);
    a = 4'b1111; b = 4'b1100; #1000 // -1 + -4 = -5
    $display("%b | %b | %b  %b    %b    | 1011 1     0", a, b, sum, carryout, overflow);
    a = 4'b1001; b = 4'b1110; #1000 //-7 + -2 = 8
    $display("%b | %b | %b  %b    %b    | 0111 1     1", a, b, sum, carryout, overflow);
    a = 4'b1110; b = 4'b1001; #1000 //-2 + -7 = 8
    $display("%b | %b | %b  %b    %b    | 0111 1     1", a, b, sum, carryout, overflow);

    /*
    Pos/Neg
    */
    a = 4'b0001; b = 4'b1001; #1000 // 1 + -7 = -6
    $display("%b | %b | %b  %b    %b    | 1010 0     0", a, b, sum, carryout, overflow);
    a = 4'b0011; b = 4'b1011; #1000 // 3 + -5 = -2
    $display("%b | %b | %b  %b    %b    | 1110 0     0", a, b, sum, carryout, overflow);
    a = 4'b0111; b = 4'b1111; #1000 // 7 + -1 = 6
    $display("%b | %b | %b  %b    %b    | 0110 1     0", a, b, sum, carryout, overflow);
    a = 4'b0011; b = 4'b1101; #1000 // 3 + -3 = 0
    $display("%b | %b | %b  %b    %b    | 0000 1     0", a, b, sum, carryout, overflow);


    /*
    Pos/Pos
    */
    a = 4'b0101; b = 4'b0010; #1000 // 5 + 2 = 7
    $display("%b | %b | %b  %b    %b    | 0111 0     0", a, b, sum, carryout, overflow);
    a = 4'b0001; b = 4'b0010; #1000 // 1 + 2 = 3
    $display("%b | %b | %b  %b    %b    | 0011 0     0", a, b, sum, carryout, overflow);
    a = 4'b0101; b = 4'b0011; #1000 // 5 + 3 = -8
    $display("%b | %b | %b  %b    %b    | 1000 0     1", a, b, sum, carryout, overflow);
    a = 4'b0111; b = 4'b0001; #1000 // 7 + 1 = -8
    $display("%b | %b | %b  %b    %b    | 1000 0     1", a, b, sum, carryout, overflow);

    /*
    Corner cases
    */
    a = 4'b0000; b = 4'b0000; #1000 // 0 + 0 = 0
    $display("%b | %b | %b  %b    %b    | 0000 0     0", a, b, sum, carryout, overflow);
    a = 4'b1000; b = 4'b0111; #1000 // -8 + 7 = -1
    $display("%b | %b | %b  %b    %b    | 1111 0     0", a, b, sum, carryout, overflow);
    a = 4'b1000; b = 4'b1000; #1000 // -8 + -8 = 0
    $display("%b | %b | %b  %b    %b    | 0000 1     1", a, b, sum, carryout, overflow);
    a = 4'b0111; b = 4'b0111; #1000 // 7 + 7 = -2
    $display("%b | %b | %b  %b    %b    | 1110 0     1", a, b, sum, carryout, overflow);

    $finish();
    end
endmodule

adder.vcd
$date
	Thu Sep 27 21:37:06 2018
$end
$version
	Icarus Verilog
$end
$timescale
	1ps
$end
$scope module testFullAdder $end
$var wire 4 ! sum [3:0] $end
$var wire 1 " overflow $end
$var wire 1 # carryout $end
$var reg 4 $ a [3:0] $end
$var reg 4 % b [3:0] $end
$scope module fulladder $end
$var wire 4 & a [3:0] $end
$var wire 1 ' a3inv $end
$var wire 4 ( b [3:0] $end
$var wire 1 ) b3inv $end
$var wire 1 * negand $end
$var wire 1 " overflow $end
$var wire 1 + posand $end
$var wire 1 , s3inv $end
$var wire 4 - sum [3:0] $end
$var wire 1 . carryout2 $end
$var wire 1 / carryout1 $end
$var wire 1 0 carryout0 $end
$var wire 1 # carryout $end
$scope module adder0 $end
$var wire 1 1 a $end
$var wire 1 2 and0 $end
$var wire 1 3 and1 $end
$var wire 1 4 b $end
$var wire 1 5 carryin $end
$var wire 1 0 carryout $end
$var wire 1 6 sum $end
$var wire 1 7 xor0 $end
$upscope $end
$scope module adder1 $end
$var wire 1 8 a $end
$var wire 1 9 and0 $end
$var wire 1 : and1 $end
$var wire 1 ; b $end
$var wire 1 0 carryin $end
$var wire 1 / carryout $end
$var wire 1 < sum $end
$var wire 1 = xor0 $end
$upscope $end
$scope module adder2 $end
$var wire 1 > a $end
$var wire 1 ? and0 $end
$var wire 1 @ and1 $end
$var wire 1 A b $end
$var wire 1 / carryin $end
$var wire 1 . carryout $end
$var wire 1 B sum $end
$var wire 1 C xor0 $end
$upscope $end
$scope module adder3 $end
$var wire 1 D a $end
$var wire 1 E and0 $end
$var wire 1 F and1 $end
$var wire 1 G b $end
$var wire 1 . carryin $end
$var wire 1 # carryout $end
$var wire 1 H sum $end
$var wire 1 I xor0 $end
$upscope $end
$upscope $end
$upscope $end
$enddefinitions $end
#0
$dumpvars
xI
xH
1G
xF
xE
1D
xC
xB
1A
x@
x?
1>
x=
x<
0;
x:
x9
18
x7
x6
05
14
x3
x2
01
x0
x/
x.
bx -
x,
x+
x*
x)
b1101 (
x'
b1110 &
b1101 %
b1110 $
x#
x"
bx !
$end
#50000
0)
17
02
1=
09
0C
1?
0I
1E
0'
03
#100000
bx1 !
bx1 -
16
0@
1.
0F
1#
0+
00
#150000
1H
b1x11 !
b1x11 -
1<
0:
#200000
0,
0/
#250000
0*
b1011 !
b1011 -
0B
#300000
0"
#1000000
04
11
b1100 %
b1100 (
b1111 $
b1111 &
#2000000
1;
08
0>
b1110 %
b1110 (
b1001 $
b1001 &
#2050000
1C
0?
#2100000
b1111 !
b1111 -
1B
0.
#2150000
b111 !
b111 -
0H
#2200000
1,
#2250000
1*
#2300000
1"
#3000000
14
0;
0A
01
18
1>
b1001 %
b1001 (
b1110 $
b1110 &
#4000000
11
08
0>
0D
b1 $
b1 &
#4050000
07
12
0=
0C
1I
0E
1'
0*
#4100000
06
10
0<
0B
b1000 !
b1000 -
1H
0#
0"
#4150000
0,
b1010 !
b1010 -
1<
#5000000
1;
18
b1011 %
b1011 (
b11 $
b11 &
#5050000
19
#5100000
1/
#5150000
b1110 !
b1110 -
1B
#6000000
1A
1>
b1111 %
b1111 (
b111 $
b111 &
#6050000
1?
#6100000
1.
#6150000
b110 !
b110 -
0H
1F
#6200000
1,
1#
#7000000
0;
0>
b1101 %
b1101 (
b11 $
b11 &
#7050000
1=
09
1C
0?
#7100000
0<
1:
0/
b0 !
b0 -
0B
1@
0.
#7150000
1/
1B
0@
1.
b1100 !
b1100 -
1H
0F
#7200000
0,
0B
1@
0.
b0 !
b0 -
0H
1F
0#
#7250000
1,
1.
b1000 !
b1000 -
1H
0F
1#
#7300000
0,
b0 !
b0 -
0H
1F
0#
#7350000
1,
1#
#8000000
04
1;
0A
0G
08
1>
b10 %
b10 (
b101 $
b101 &
#8050000
17
02
0I
1)
#8100000
16
00
b1001 !
b1001 -
1H
0F
1+
#8150000
0,
b1011 !
b1011 -
1<
0:
0#
1"
#8200000
0/
#8250000
b1111 !
b1111 -
1B
0@
#8300000
0.
#8350000
b111 !
b111 -
0H
0+
#8400000
1,
0"
#9000000
0>
b1 $
b1 &
#9050000
0C
#9100000
b11 !
b11 -
0B
#10000000
14
1>
b11 %
b11 (
b101 $
b101 &
#10050000
07
12
1C
#10100000
06
10
b110 !
b110 -
1B
#10150000
b100 !
b100 -
0<
1:
#10200000
1/
#10250000
b0 !
b0 -
0B
1@
#10300000
1.
#10350000
b1000 !
b1000 -
1H
1+
#10400000
0,
1"
#11000000
0;
18
b1 %
b1 (
b111 $
b111 &
#12000000
04
01
08
0>
b0 %
b0 (
b0 $
b0 &
#12050000
02
0=
0C
#12100000
00
1<
0:
b1110 !
b1110 -
1B
0@
#12150000
b1100 !
b1100 -
0<
0/
0.
#12200000
0B
b0 !
b0 -
0H
0+
#12250000
1,
0"
#13000000
14
1;
1A
1D
b111 %
b111 (
b1000 $
b1000 &
#13050000
17
1=
1C
1I
0'
#13100000
16
1<
1B
b1111 !
b1111 -
1H
#13150000
0,
#14000000
04
0;
0A
1G
b1000 %
b1000 (
#14050000
07
0=
0C
0I
1E
0)
#14100000
06
0<
0B
b0 !
b0 -
0H
1#
#14150000
1,
#14200000
1*
#14250000
1"
#15000000
14
1;
1A
0G
11
18
1>
0D
b111 %
b111 (
b111 $
b111 &
#15050000
1)
12
19
1?
0E
1'
0*
#15100000
10
1/
1.
0#
0"
#15150000
1<
1B
b1110 !
b1110 -
1H
1+
#15200000
0,
1"
